[{"date":"2024-12-21","list":[{"horse_name":"アサカラキング","horse_url":"https://db.netkeiba.com/horse/2020105154","horse_age":"牡4歳","horse_color":"鹿毛","b_ml":"キズナ","b_ml_2":"キングヘイロー","b_fml":"アサカラヴァーズ","race_name":null,"race_id":202408070711}]},{"date":"2024-12-22","list":[{"horse_name":"ツルマウカタチ","horse_url":"https://db.netkeiba.com/horse/2021102106","horse_age":"牡3歳","horse_color":"栗毛","b_ml":"ヤングマンパワー","b_ml_2":"キングヘイロー","b_fml":"ハイタッチクイーン","race_name":null,"race_id":202406050810},{"horse_name":"ディープボンド","horse_url":"https://db.netkeiba.com/horse/2017102170","horse_age":"牡7歳","horse_color":"青鹿毛","b_ml":"キズナ","b_ml_2":"キングヘイロー","b_fml":"ゼフィランサス","race_name":null,"race_id":202406050811},{"horse_name":"ドンアミティエ","horse_url":"https://db.netkeiba.com/horse/2020106006","horse_age":"牡4歳","horse_color":"黒鹿毛","b_ml":"アジアエクスプレス","b_ml_2":"キングヘイロー","b_fml":"クラシックス","race_name":null,"race_id":202408070811}]}]
